fourier_sine/__init__.py
fourier_sine-0.4.0.dist-info/WHEEL
fourier_sine-0.4.0.dist-info/METADATA
fourier_sine-0.4.0.dist-info/RECORD
