Metadata-Version: 2.1
Name: fourier-sine
Version: 0.4.0
Summary: Fourier Analysis with sine waves
Author: Andrew Matte
Author-email: andrew.matte@gmail.com
Requires-Python: >=3.6
Classifier: Programming Language :: Python :: 3
Classifier: Programming Language :: Python :: 3.10
Classifier: Programming Language :: Python :: 3.6
Classifier: Programming Language :: Python :: 3.7
Classifier: Programming Language :: Python :: 3.8
Classifier: Programming Language :: Python :: 3.9
